repl_python_wakatime/__init__.py
repl_python_wakatime/_metainfo.py
repl_python_wakatime/_version.py
repl_python_wakatime/py.typed
repl_python_wakatime/backends/__init__.py
repl_python_wakatime/backends/codestats.py
repl_python_wakatime/backends/wakatime.py
repl_python_wakatime/frontends/__init__.py
repl_python_wakatime/frontends/gdb.py
repl_python_wakatime/frontends/ipython.py
repl_python_wakatime/frontends/ptpython.py
repl_python_wakatime/frontends/python.py
repl_python_wakatime-1.0.3.dist-info/licenses/LICENSE
repl_python_wakatime-1.0.3.dist-info/METADATA
repl_python_wakatime-1.0.3.dist-info/WHEEL
repl_python_wakatime-1.0.3.dist-info/top_level.txt
repl_python_wakatime-1.0.3.dist-info/RECORD
