Metadata-Version: 2.4
Name: repl-python-wakatime
Version: 1.0.3
Summary: Python REPL plugin for automatic time tracking and metrics generated from your programming activity
Author-email: Wu Zhenyu <wuzhenyu@ustc.edu>
License: GPL v3
Project-URL: Homepage, https://repl-python-wakatime.readthedocs.io
Project-URL: Download, https://github.com/wakatime/repl-python-wakatime/releases
Project-URL: Bug Report, https://github.com/wakatime/repl-python-wakatime/issues
Project-URL: Source, https://github.com/wakatime/repl-python-wakatime
Keywords: wakatime,plugin,python,ipython,ptpython
Classifier: Development Status :: 3 - Alpha
Classifier: Intended Audience :: Developers
Classifier: Topic :: Software Development :: Build Tools
Classifier: License :: OSI Approved :: GNU General Public License v3 (GPLv3)
Classifier: Operating System :: Microsoft :: Windows
Classifier: Operating System :: POSIX
Classifier: Operating System :: Unix
Classifier: Operating System :: MacOS
Classifier: Programming Language :: Python :: 3 :: Only
Classifier: Programming Language :: Python :: 3
Classifier: Programming Language :: Python :: 3.7
Classifier: Programming Language :: Python :: 3.8
Classifier: Programming Language :: Python :: 3.9
Classifier: Programming Language :: Python :: 3.10
Classifier: Programming Language :: Python :: 3.11
Classifier: Programming Language :: Python :: Implementation :: CPython
Classifier: Programming Language :: Python :: Implementation :: PyPy
Requires-Python: >=3.11
License-File: LICENSE
Provides-Extra: dev
Requires-Dist: pytest-cov; extra == "dev"
Provides-Extra: codestats
Requires-Dist: aiohttp; extra == "codestats"
Requires-Dist: keyring; extra == "codestats"
Provides-Extra: ipython
Requires-Dist: ipython; extra == "ipython"
Provides-Extra: ptpython
Requires-Dist: ptpython; extra == "ptpython"
Provides-Extra: ptipython
Requires-Dist: ptpython[ptipython]; extra == "ptipython"
Dynamic: license-file
